LICENSE
MANIFEST.in
README.md
pyproject.toml
setup.cfg
setup.py
drf_user_activity_tracker_mongodb/__init__.py
drf_user_activity_tracker_mongodb/admin.py
drf_user_activity_tracker_mongodb/apps.py
drf_user_activity_tracker_mongodb/events.py
drf_user_activity_tracker_mongodb/insert_log_into_database.py
drf_user_activity_tracker_mongodb/models.py
drf_user_activity_tracker_mongodb/permissions.py
drf_user_activity_tracker_mongodb/serializers.py
drf_user_activity_tracker_mongodb/start_logger_when_server_starts.py
drf_user_activity_tracker_mongodb/tests.py
drf_user_activity_tracker_mongodb/urls.py
drf_user_activity_tracker_mongodb/utils.py
drf_user_activity_tracker_mongodb/views.py
drf_user_activity_tracker_mongodb.egg-info/PKG-INFO
drf_user_activity_tracker_mongodb.egg-info/SOURCES.txt
drf_user_activity_tracker_mongodb.egg-info/dependency_links.txt
drf_user_activity_tracker_mongodb.egg-info/requires.txt
drf_user_activity_tracker_mongodb.egg-info/top_level.txt
drf_user_activity_tracker_mongodb/geo_databases/GeoLite2-Country.mmdb
drf_user_activity_tracker_mongodb/management/commands/get_url_names.py
drf_user_activity_tracker_mongodb/middleware/__init__.py
drf_user_activity_tracker_mongodb/middleware/activity_tracker_middleware.py
drf_user_activity_tracker_mongodb/migrations/0001_initial.py
drf_user_activity_tracker_mongodb/migrations/__init__.py
drf_user_activity_tracker_mongodb/templates/activity_log/admin/change_detail.html
drf_user_activity_tracker_mongodb/templates/activity_log/admin/change_list_v2.html
drf_user_activity_tracker_mongodb/templates/activity_log/admin/change_list_v3.html
drf_user_activity_tracker_mongodb/templatetags/__init__.py
drf_user_activity_tracker_mongodb/templatetags/tagger.py