Metadata-Version: 2.1
Name: drf-user-activity-tracker-mongodb
Version: 1.4.7
Summary: A Django app to logs users activities in mongodb database.
Home-page: https://github.com/bigmo94/drf-user-activity-tracker-mongodb
Author: Mohamad Rezaie
Author-email: m.rezaie94@gmail.com
License: MIT
Classifier: Environment :: Web Environment
Classifier: Framework :: Django
Classifier: Intended Audience :: Developers
Classifier: License :: OSI Approved :: MIT License
Classifier: Operating System :: OS Independent
Classifier: Programming Language :: Python
Classifier: Programming Language :: Python :: 3
Requires-Python: >=3.8
License-File: LICENSE
